{
	"name":"Lesser Healing Wave",
	"description":"Heals friendly target for ${powerMin} to ${powerMax}.",
	"ranks":[
		{	"rank":1,
			"level":20,
			"cost":105,
			"range":40,
			"baseCastSpeed":1.5,
			"powerMin":162,
			"powerMax":187,
			"tickInterval":0,
			"tickDuration":0,
			"tickPower":0
		},
		{	"rank":2,
			"level":28,
			"cost":145,
			"range":40,
			"baseCastSpeed":1.5,
			"powerMin":247,
			"powerMax":282,
			"tickInterval":0,
			"tickDuration":0,
			"tickPower":0
		},
		{	"rank":3,
			"level":36,
			"cost":185,
			"range":40,
			"baseCastSpeed":1.5,
			"powerMin":337,
			"powerMax":382,
			"tickInterval":0,
			"tickDuration":0,
			"tickPower":0
		},
		{	"rank":4,
			"level":44,
			"cost":235,
			"range":40,
			"baseCastSpeed":1.5,
			"powerMin":458,
			"powerMax":515,
			"tickInterval":0,
			"tickDuration":0,
			"tickPower":0
		},
		{	"rank":5,
			"level":52,
			"cost":305,
			"range":40,
			"baseCastSpeed":1.5,
			"powerMin":631,
			"powerMax":706,
			"tickInterval":0,
			"tickDuration":0,
			"tickPower":0
		},
		{	"rank":6,
			"level":60,
			"cost":380,
			"range":40,
			"baseCastSpeed":1.5,
			"powerMin":832,
			"powerMax":929,
			"tickInterval":0,
			"tickDuration":0,
			"tickPower":0
		}
	]
}